ashi/__init__.py
ashi/_version.py
ashi/welcome.py
ashi-0.0.0.dist-info/licenses/LICENSE
ashi-0.0.0.dist-info/METADATA
ashi-0.0.0.dist-info/WHEEL
ashi-0.0.0.dist-info/top_level.txt
ashi-0.0.0.dist-info/RECORD
